wstan/__init__.py
wstan/client.py
wstan/relay.py
wstan/server.py
wstan/utils.py
wstan/web_panel.py
wstan/autobahn/__init__.py
wstan/autobahn/util.py
wstan/autobahn/asyncio/__init__.py
wstan/autobahn/asyncio/websocket.py
wstan/autobahn/websocket/__init__.py
wstan/autobahn/websocket/protocol.py
wstan/autobahn/websocket/types.py
wstan/autobahn/websocket/utf8validator.py
wstan/autobahn/websocket/xormasker.py
wstan/static/favicon.ico
wstan/static/index.html
wstan/static/main-VLHZVYSC.js
wstan/static/polyfills-FFHMD2TL.js
wstan/static/styles-R55LHO57.css
wstan/static/tunnel-white.svg
wstan/static/tunnel.svg
wstan-0.5.1.dist-info/licenses/LICENSE
wstan-0.5.1.dist-info/METADATA
wstan-0.5.1.dist-info/WHEEL
wstan-0.5.1.dist-info/entry_points.txt
wstan-0.5.1.dist-info/top_level.txt
wstan-0.5.1.dist-info/RECORD
