Metadata-Version: 2.4
Name: wstan
Version: 0.5.1
Summary: Tunneling TCP/UDP in WebSocket
Author-email: krrr <guogaishiwo@gmail.com>
License-Expression: MIT
Project-URL: homepage, https://github.com/krrr/wstan
Keywords: proxy,tunnel,websocket
Classifier: Topic :: Internet :: Proxy Servers
Classifier: Operating System :: OS Independent
Classifier: Programming Language :: Python :: 3.10
Classifier: Programming Language :: Python :: 3.11
Classifier: Programming Language :: Python :: 3.12
Classifier: Programming Language :: Python :: 3 :: Only
Requires-Python: >=3.10
License-File: LICENSE
Requires-Dist: cryptography
Requires-Dist: sanic
Provides-Extra: faster-event-loop
Requires-Dist: uvloop; extra == "faster-event-loop"
Dynamic: license-file
